rickle/__init__.py
rickle/__version__.py
rickle/cli/__init__.py
rickle/cli/__main__.py
rickle/cli/conv.py
rickle/cli/obj.py
rickle/cli/schema.py
rickle/cli/serve.py
rickle/net.py
rickle/schema.py
rickle/tools.py
rickle-1.2.4.dist-info/entry_points.txt
rickle-1.2.4.dist-info/LICENSE
rickle-1.2.4.dist-info/METADATA
rickle-1.2.4.dist-info/WHEEL
rickle-1.2.4.dist-info/RECORD
